findrefs/__init__.py
findrefs/models.py
findrefs/migrations/0001_initial.py
findrefs/migrations/0002_alter_artifactreference_artifact_and_more.py
findrefs/migrations/__init__.py
findrefs-0.2.0.dist-info/LICENSE
findrefs-0.2.0.dist-info/WHEEL
findrefs-0.2.0.dist-info/METADATA
findrefs-0.2.0.dist-info/RECORD
